{
  "hash": "4b92606d",
  "configHash": "dbb35a55",
  "lockfileHash": "25582481",
  "browserHash": "075ab37d",
  "optimized": {
    "@angular/core": {
      "src": "../../../../../../node_modules/@angular/core/fesm2022/core.mjs",
      "file": "@angular_core.js",
      "fileHash": "e3a29ed5",
      "needsInterop": false
    },
    "@angular/forms": {
      "src": "../../../../../../node_modules/@angular/forms/fesm2022/forms.mjs",
      "file": "@angular_forms.js",
      "fileHash": "5b742618",
      "needsInterop": false
    },
    "@angular/platform-browser": {
      "src": "../../../../../../node_modules/@angular/platform-browser/fesm2022/platform-browser.mjs",
      "file": "@angular_platform-browser.js",
      "fileHash": "22909383",
      "needsInterop": false
    },
    "@angular/platform-server/init": {
      "src": "../../../../../../node_modules/@angular/platform-server/fesm2022/init.mjs",
      "file": "@angular_platform-server_init.js",
      "fileHash": "3546e0ea",
      "needsInterop": false
    },
    "@angular/router": {
      "src": "../../../../../../node_modules/@angular/router/fesm2022/router.mjs",
      "file": "@angular_router.js",
      "fileHash": "22f0c03d",
      "needsInterop": false
    },
    "@angular/ssr": {
      "src": "../../../../../../node_modules/@angular/ssr/fesm2022/ssr.mjs",
      "file": "@angular_ssr.js",
      "fileHash": "214870f1",
      "needsInterop": false
    },
    "@angular/ssr/node": {
      "src": "../../../../../../node_modules/@angular/ssr/fesm2022/node.mjs",
      "file": "@angular_ssr_node.js",
      "fileHash": "1c96260c",
      "needsInterop": false
    },
    "express": {
      "src": "../../../../../../node_modules/express/index.js",
      "file": "express.js",
      "fileHash": "42ea9644",
      "needsInterop": true
    },
    "rxjs": {
      "src": "../../../../../../node_modules/rxjs/dist/cjs/index.js",
      "file": "rxjs.js",
      "fileHash": "45035f14",
      "needsInterop": true
    }
  },
  "chunks": {
    "xhr2-E5RTESSH": {
      "file": "xhr2-E5RTESSH.js"
    },
    "chunk-WDBKEZCX": {
      "file": "chunk-WDBKEZCX.js"
    },
    "chunk-2IUF7FZV": {
      "file": "chunk-2IUF7FZV.js"
    },
    "chunk-34WZWJKV": {
      "file": "chunk-34WZWJKV.js"
    },
    "chunk-IRI7HUOR": {
      "file": "chunk-IRI7HUOR.js"
    },
    "chunk-CP735FV6": {
      "file": "chunk-CP735FV6.js"
    },
    "chunk-O5J3CNTX": {
      "file": "chunk-O5J3CNTX.js"
    },
    "chunk-6DU2HRTW": {
      "file": "chunk-6DU2HRTW.js"
    }
  }
}